ymvas/__init__.py
ymvas/api.py
ymvas/stock.py
ymvas_py-1.1.1.dist-info/LICENSE.TXT
ymvas_py-1.1.1.dist-info/METADATA
ymvas_py-1.1.1.dist-info/WHEEL
ymvas_py-1.1.1.dist-info/top_level.txt
ymvas_py-1.1.1.dist-info/RECORD
